threatbus_zeek/__init__.py
threatbus_zeek/message_mapping.py
threatbus_zeek/plugin.py
threatbus_zeek/test_message_mapping.py
threatbus_zeek-2022.5.16.dist-info/METADATA
threatbus_zeek-2022.5.16.dist-info/WHEEL
threatbus_zeek-2022.5.16.dist-info/entry_points.txt
threatbus_zeek-2022.5.16.dist-info/top_level.txt
threatbus_zeek-2022.5.16.dist-info/RECORD
